README.txt
setup.py
Products/__init__.py
Products.slideshowfolder.egg-info/PKG-INFO
Products.slideshowfolder.egg-info/SOURCES.txt
Products.slideshowfolder.egg-info/dependency_links.txt
Products.slideshowfolder.egg-info/entry_points.txt
Products.slideshowfolder.egg-info/namespace_packages.txt
Products.slideshowfolder.egg-info/not-zip-safe
Products.slideshowfolder.egg-info/requires.txt
Products.slideshowfolder.egg-info/top_level.txt
Products/slideshowfolder/CHANGES.txt
Products/slideshowfolder/LICENSE.txt
Products/slideshowfolder/README.txt
Products/slideshowfolder/TODO.txt
Products/slideshowfolder/__init__.py
Products/slideshowfolder/browser.py
Products/slideshowfolder/config.py
Products/slideshowfolder/configure.zcml
Products/slideshowfolder/interfaces.py
Products/slideshowfolder/slideshowsetting.py
Products/slideshowfolder/version.txt
Products/slideshowfolder/Extensions/Install.py
Products/slideshowfolder/Extensions/__init__.py
Products/slideshowfolder/Extensions/utils.py
Products/slideshowfolder/i18n/plone-slideshowfolder.pot
Products/slideshowfolder/locales/slideshowfolder.pot
Products/slideshowfolder/profiles/default/actions.xml
Products/slideshowfolder/profiles/default/metadata.xml
Products/slideshowfolder/profiles/default/skins.xml
Products/slideshowfolder/profiles/plone3/actions.xml
Products/slideshowfolder/profiles/plone3/skins.xml
Products/slideshowfolder/skins/slideshowfolder/controller-first.gif
Products/slideshowfolder/skins/slideshowfolder/controller-last.gif
Products/slideshowfolder/skins/slideshowfolder/controller-next.gif
Products/slideshowfolder/skins/slideshowfolder/controller-pause.gif
Products/slideshowfolder/skins/slideshowfolder/controller-play.gif
Products/slideshowfolder/skins/slideshowfolder/controller-prev.gif
Products/slideshowfolder/skins/slideshowfolder/controller.png
Products/slideshowfolder/skins/slideshowfolder/folder_slideshow.pt
Products/slideshowfolder/skins/slideshowfolder/folder_slideshow.pt.metadata
Products/slideshowfolder/skins/slideshowfolder/loader-0.png
Products/slideshowfolder/skins/slideshowfolder/loader-1.gif
Products/slideshowfolder/skins/slideshowfolder/loader-1.png
Products/slideshowfolder/skins/slideshowfolder/loader-10.png
Products/slideshowfolder/skins/slideshowfolder/loader-11.png
Products/slideshowfolder/skins/slideshowfolder/loader-2.gif
Products/slideshowfolder/skins/slideshowfolder/loader-2.png
