Metadata-Version: 1.0
Name: Products.slideshowfolder
Version: 4.0
Summary: Slideshow Folder provides a simple, elegant animated slideshow for Plone.
Home-page: http://plone.org/products/slideshowfolder
Author: Johnpaul Burbank, Jon Baldivieso, David Glick, et al
Author-email: davidglick@onenw.org
License: GPL
Keywords: plone slideshow album mootools javascript
Platform: UNKNOWN
Classifier: Framework :: Plone
Classifier: Programming Language :: Python
Classifier: Development Status :: 5 - Production/Stable
Classifier: License :: OSI Approved :: GNU General Public License (GPL)
